bagua_python_sdk-1.0.2.dist-info/METADATA
bagua_python_sdk-1.0.2.dist-info/WHEEL
bagua_python_sdk-1.0.2.dist-info/licenses/LICENSE
bagua.libs/libgcc_s-1e52349c.so.1
bagua/bagua.pyi
bagua/__init__.py
bagua/bagua.pypy310-pp73-x86_64-linux-gnu.so
bagua_python_sdk-1.0.2.dist-info/RECORD
